agent_harness/__init__.py
agent_harness/agent_harness.py
agent_harness/api_comms.py
agent_harness-0.1.10.dist-info/AUTHORS.rst
agent_harness-0.1.10.dist-info/LICENSE
agent_harness-0.1.10.dist-info/METADATA
agent_harness-0.1.10.dist-info/WHEEL
agent_harness-0.1.10.dist-info/entry_points.txt
agent_harness-0.1.10.dist-info/top_level.txt
agent_harness-0.1.10.dist-info/RECORD
