Metadata-Version: 2.1
Name: agent-harness
Version: 0.1.10
Summary: AI Maintainer Agent Harness for our benchmarking and Marketplace API and platform
Home-page: https://github.com/dschonholtz/agent_harness
Author: Douglas Schonholtz
Author-email: douglas@ai-maintainer.com
License: MIT license
Keywords: agent_harness
Platform: UNKNOWN
Classifier: Development Status :: 2 - Pre-Alpha
Classifier: Intended Audience :: Developers
Classifier: License :: OSI Approved :: MIT License
Classifier: Natural Language :: English
Classifier: Programming Language :: Python :: 3
Classifier: Programming Language :: Python :: 3.8
Classifier: Programming Language :: Python :: 3.9
Classifier: Programming Language :: Python :: 3.10
Requires-Python: >=3.8
Requires-Dist: Click >=7.0
Requires-Dist: agent-marketplace-sdk ==0.1.6
Requires-Dist: docker >=4.2.2
Requires-Dist: ai-maintainer-git-util >=0.1.1
